mplc/__init__.py
mplc/constants.py
mplc/contributivity.py
mplc/corruption.py
mplc/dataset.py
mplc/experiment.py
mplc/models.py
mplc/partner.py
mplc/scenario.py
mplc/splitter.py
mplc/utils.py
mplc/multi_partner_learning/__init__.py
mplc/multi_partner_learning/basic_mpl.py
mplc/multi_partner_learning/fast_mpl.py
mplc/multi_partner_learning/utils.py
tests/__init__.py
tests/contrib_end_to_end_test.py
tests/ml_perf_end_to_end_tests.py
tests/test_utils.py
tests/unit_tests.py
mplc-0.4.2.dist-info/LICENSE
mplc-0.4.2.dist-info/METADATA
mplc-0.4.2.dist-info/WHEEL
mplc-0.4.2.dist-info/top_level.txt
mplc-0.4.2.dist-info/RECORD
