Metadata-Version: 2.1
Name: mplc
Version: 0.4.2
Summary: A distributed-learning package for the study of multi-partner learning approaches and contributivity measurement methods
Home-page: https://github.com/LabeliaLabs/distributed-learning-contributivity.git
Author: LabeliaLabs
Author-email: contact@labelia.org
License: Apache 2.0
Keywords: library,substra,labelia,machine learning,contributivity,multi-partner learning,distributed learning
Platform: UNKNOWN
Classifier: Programming Language :: Python :: 3
Classifier: Operating System :: OS Independent
Requires-Python: >=3.6
Requires-Dist: h5py (~=3.1.0)
Requires-Dist: joblib (==1.0.0)
Requires-Dist: librosa (==0.8.1)
Requires-Dist: matplotlib (==3.3.3)
Requires-Dist: numpy (==1.19.5)
Requires-Dist: scipy (==1.5.4)
Requires-Dist: scikit-learn (==0.23.2)
Requires-Dist: pandas (==1.1.5)
Requires-Dist: seaborn (==0.11.0)
Requires-Dist: loguru (==0.5.3)
Requires-Dist: tensorflow (==2.5.1)
Requires-Dist: ruamel.yaml (==0.16.12)
